[{"Date":1666051333000,"Annex Weight Room":170,"Extension Weight Room":57,"Main Weight Room":107,"Weight Rooms":98},{"Date":1666051634000,"Annex Weight Room":173,"Extension Weight Room":55,"Main Weight Room":111,"Weight Rooms":102},{"Date":1666051935000,"Annex Weight Room":180,"Extension Weight Room":57,"Main Weight Room":107,"Weight Rooms":102},{"Date":1666052235000,"Annex Weight Room":176,"Extension Weight Room":62,"Main Weight Room":105,"Weight Rooms":101},{"Date":1666052536000,"Annex Weight Room":180,"Extension Weight Room":62,"Main Weight Room":103,"Weight Rooms":100},{"Date":1666052836000,"Annex Weight Room":166,"Extension Weight Room":60,"Main Weight Room":108,"Weight Rooms":100},{"Date":1666053137000,"Annex Weight Room":176,"Extension Weight Room":70,"Main Weight Room":100,"Weight Rooms":100},{"Date":1666053438000,"Annex Weight Room":180,"Extension Weight Room":65,"Main Weight Room":105,"Weight Rooms":102},{"Date":1666053738000,"Annex Weight Room":183,"Extension Weight Room":52,"Main Weight Room":108,"Weight Rooms":102},{"Date":1666054039000,"Annex Weight Room":196,"Extension Weight Room":55,"Main Weight Room":105,"Weight Rooms":103},{"Date":1666054340000,"Annex Weight Room":196,"Extension Weight Room":67,"Main Weight Room":101,"Weight Rooms":104},{"Date":1666054640000,"Annex Weight Room":163,"Extension Weight Room":72,"Main Weight Room":106,"Weight Rooms":102},{"Date":1666054941000,"Annex Weight Room":163,"Extension Weight Room":67,"Main Weight Room":100,"Weight Rooms":97},{"Date":1666055241000,"Annex Weight Room":163,"Extension Weight Room":57,"Main Weight Room":97,"Weight Rooms":93},{"Date":1666055542000,"Annex Weight Room":170,"Extension Weight Room":35,"Main Weight Room":95,"Weight Rooms":87},{"Date":1666055843000,"Annex Weight Room":146,"Extension Weight Room":45,"Main Weight Room":98,"Weight Rooms":87},{"Date":1666056143000,"Annex Weight Room":170,"Extension Weight Room":47,"Main Weight Room":97,"Weight Rooms":93},{"Date":1666056444000,"Annex Weight Room":166,"Extension Weight Room":70,"Main Weight Room":93,"Weight Rooms":95},{"Date":1666056744000,"Annex Weight Room":156,"Extension Weight Room":62,"Main Weight Room":106,"Weight Rooms":98},{"Date":1666057045000,"Annex Weight Room":176,"Extension Weight Room":57,"Main Weight Room":107,"Weight Rooms":101},{"Date":1666057346000,"Annex Weight Room":190,"Extension Weight Room":47,"Main Weight Room":108,"Weight Rooms":102},{"Date":1666057646000,"Annex Weight Room":173,"Extension Weight Room":45,"Main Weight Room":117,"Weight Rooms":102},{"Date":1666057947000,"Annex Weight Room":180,"Extension Weight Room":42,"Main Weight Room":112,"Weight Rooms":100},{"Date":1666058247000,"Annex Weight Room":193,"Extension Weight Room":42,"Main Weight Room":108,"Weight Rooms":101},{"Date":1666058548000,"Annex Weight Room":206,"Extension Weight Room":40,"Main Weight Room":110,"Weight Rooms":104},{"Date":1666058849000,"Annex Weight Room":186,"Extension Weight Room":42,"Main Weight Room":113,"Weight Rooms":102},{"Date":1666059149000,"Annex Weight Room":190,"Extension Weight Room":25,"Main Weight Room":122,"Weight Rooms":103},{"Date":1666059450000,"Annex Weight Room":200,"Extension Weight Room":42,"Main Weight Room":106,"Weight Rooms":101},{"Date":1666059751000,"Annex Weight Room":206,"Extension Weight Room":37,"Main Weight Room":105,"Weight Rooms":100},{"Date":1666060051000,"Annex Weight Room":203,"Extension Weight Room":42,"Main Weight Room":103,"Weight Rooms":100},{"Date":1666060352000,"Annex Weight Room":190,"Extension Weight Room":35,"Main Weight Room":111,"Weight Rooms":100},{"Date":1666060652000,"Annex Weight Room":173,"Extension Weight Room":50,"Main Weight Room":112,"Weight Rooms":100},{"Date":1666060953000,"Annex Weight Room":190,"Extension Weight Room":37,"Main Weight Room":113,"Weight Rooms":102},{"Date":1666061254000,"Annex Weight Room":200,"Extension Weight Room":32,"Main Weight Room":116,"Weight Rooms":102},{"Date":1666061554000,"Annex Weight Room":186,"Extension Weight Room":47,"Main Weight Room":116,"Weight Rooms":105},{"Date":1666061855000,"Annex Weight Room":206,"Extension Weight Room":50,"Main Weight Room":102,"Weight Rooms":102},{"Date":1666062155000,"Annex Weight Room":190,"Extension Weight Room":67,"Main Weight Room":97,"Weight Rooms":100},{"Date":1666062456000,"Annex Weight Room":170,"Extension Weight Room":80,"Main Weight Room":101,"Weight Rooms":102},{"Date":1666062757000,"Annex Weight Room":166,"Extension Weight Room":60,"Main Weight Room":112,"Weight Rooms":102},{"Date":1666063057000,"Annex Weight Room":170,"Extension Weight Room":70,"Main Weight Room":107,"Weight Rooms":102},{"Date":1666063358000,"Annex Weight Room":173,"Extension Weight Room":67,"Main Weight Room":110,"Weight Rooms":104},{"Date":1666063658000,"Annex Weight Room":176,"Extension Weight Room":67,"Main Weight Room":107,"Weight Rooms":104},{"Date":1666063959000,"Annex Weight Room":156,"Extension Weight Room":70,"Main Weight Room":113,"Weight Rooms":104},{"Date":1666064260000,"Annex Weight Room":170,"Extension Weight Room":57,"Main Weight Room":116,"Weight Rooms":104},{"Date":1666064560000,"Annex Weight Room":163,"Extension Weight Room":65,"Main Weight Room":112,"Weight Rooms":103},{"Date":1666064861000,"Annex Weight Room":173,"Extension Weight Room":70,"Main Weight Room":110,"Weight Rooms":105},{"Date":1666065162000,"Annex Weight Room":190,"Extension Weight Room":57,"Main Weight Room":111,"Weight Rooms":106},{"Date":1666065462000,"Annex Weight Room":176,"Extension Weight Room":47,"Main Weight Room":116,"Weight Rooms":104},{"Date":1666065763000,"Annex Weight Room":183,"Extension Weight Room":60,"Main Weight Room":110,"Weight Rooms":104},{"Date":1666066063000,"Annex Weight Room":183,"Extension Weight Room":42,"Main Weight Room":120,"Weight Rooms":106},{"Date":1666066364000,"Annex Weight Room":196,"Extension Weight Room":60,"Main Weight Room":105,"Weight Rooms":104},{"Date":1666066665000,"Annex Weight Room":193,"Extension Weight Room":52,"Main Weight Room":112,"Weight Rooms":106},{"Date":1666066965000,"Annex Weight Room":193,"Extension Weight Room":60,"Main Weight Room":117,"Weight Rooms":110},{"Date":1666067266000,"Annex Weight Room":173,"Extension Weight Room":67,"Main Weight Room":111,"Weight Rooms":105},{"Date":1666067566000,"Annex Weight Room":163,"Extension Weight Room":62,"Main Weight Room":118,"Weight Rooms":106},{"Date":1666067867000,"Annex Weight Room":183,"Extension Weight Room":75,"Main Weight Room":102,"Weight Rooms":104},{"Date":1666068168000,"Annex Weight Room":186,"Extension Weight Room":52,"Main Weight Room":112,"Weight Rooms":104},{"Date":1666068468000,"Annex Weight Room":203,"Extension Weight Room":50,"Main Weight Room":107,"Weight Rooms":104},{"Date":1666068769000,"Annex Weight Room":173,"Extension Weight Room":55,"Main Weight Room":114,"Weight Rooms":104},{"Date":1666069070000,"Annex Weight Room":193,"Extension Weight Room":57,"Main Weight Room":108,"Weight Rooms":105},{"Date":1666069370000,"Annex Weight Room":193,"Extension Weight Room":60,"Main Weight Room":105,"Weight Rooms":104},{"Date":1666069671000,"Annex Weight Room":196,"Extension Weight Room":50,"Main Weight Room":112,"Weight Rooms":106},{"Date":1666069971000,"Annex Weight Room":206,"Extension Weight Room":62,"Main Weight Room":105,"Weight Rooms":107},{"Date":1666070272000,"Annex Weight Room":196,"Extension Weight Room":45,"Main Weight Room":112,"Weight Rooms":104},{"Date":1666070573000,"Annex Weight Room":186,"Extension Weight Room":37,"Main Weight Room":116,"Weight Rooms":102},{"Date":1666070873000,"Annex Weight Room":193,"Extension Weight Room":42,"Main Weight Room":97,"Weight Rooms":95},{"Date":1666071174000,"Annex Weight Room":180,"Extension Weight Room":40,"Main Weight Room":97,"Weight Rooms":92},{"Date":1666071474000,"Annex Weight Room":166,"Extension Weight Room":42,"Main Weight Room":86,"Weight Rooms":84},{"Date":1666071775000,"Annex Weight Room":166,"Extension Weight Room":27,"Main Weight Room":93,"Weight Rooms":84},{"Date":1666072076000,"Annex Weight Room":156,"Extension Weight Room":22,"Main Weight Room":75,"Weight Rooms":70},{"Date":1666072376000,"Annex Weight Room":140,"Extension Weight Room":15,"Main Weight Room":62,"Weight Rooms":58},{"Date":1666072677000,"Annex Weight Room":96,"Extension Weight Room":0,"Main Weight Room":41,"Weight Rooms":32},{"Date":1666101838000,"Annex Weight Room":33,"Extension Weight Room":12,"Main Weight Room":38,"Weight Rooms":30},{"Date":1666102138000,"Annex Weight Room":53,"Extension Weight Room":15,"Main Weight Room":45,"Weight Rooms":38},{"Date":1666102439000,"Annex Weight Room":63,"Extension Weight Room":22,"Main Weight Room":51,"Weight Rooms":46},{"Date":1666102740000,"Annex Weight Room":70,"Extension Weight Room":32,"Main Weight Room":57,"Weight Rooms":52},{"Date":1666103040000,"Annex Weight Room":83,"Extension Weight Room":42,"Main Weight Room":55,"Weight Rooms":57},{"Date":1666103341000,"Annex Weight Room":93,"Extension Weight Room":52,"Main Weight Room":57,"Weight Rooms":63},{"Date":1666103641000,"Annex Weight Room":86,"Extension Weight Room":60,"Main Weight Room":62,"Weight Rooms":66},{"Date":1666103942000,"Annex Weight Room":76,"Extension Weight Room":67,"Main Weight Room":75,"Weight Rooms":73},{"Date":1666104243000,"Annex Weight Room":76,"Extension Weight Room":77,"Main Weight Room":73,"Weight Rooms":75},{"Date":1666104543000,"Annex Weight Room":90,"Extension Weight Room":80,"Main Weight Room":81,"Weight Rooms":82},{"Date":1666104844000,"Annex Weight Room":100,"Extension Weight Room":70,"Main Weight Room":81,"Weight Rooms":82},{"Date":1666105145000,"Annex Weight Room":86,"Extension Weight Room":72,"Main Weight Room":75,"Weight Rooms":76},{"Date":1666105445000,"Annex Weight Room":80,"Extension Weight Room":72,"Main Weight Room":78,"Weight Rooms":77},{"Date":1666105746000,"Annex Weight Room":86,"Extension Weight Room":70,"Main Weight Room":78,"Weight Rooms":78},{"Date":1666106046000,"Annex Weight Room":86,"Extension Weight Room":72,"Main Weight Room":68,"Weight Rooms":73},{"Date":1666106347000,"Annex Weight Room":73,"Extension Weight Room":72,"Main Weight Room":66,"Weight Rooms":69},{"Date":1666106648000,"Annex Weight Room":76,"Extension Weight Room":70,"Main Weight Room":66,"Weight Rooms":69},{"Date":1666106948000,"Annex Weight Room":70,"Extension Weight Room":75,"Main Weight Room":66,"Weight Rooms":70},{"Date":1666107249000,"Annex Weight Room":83,"Extension Weight Room":47,"Main Weight Room":67,"Weight Rooms":65},{"Date":1666107549000,"Annex Weight Room":80,"Extension Weight Room":62,"Main Weight Room":67,"Weight Rooms":70},{"Date":1666107850000,"Annex Weight Room":80,"Extension Weight Room":60,"Main Weight Room":62,"Weight Rooms":65},{"Date":1666108151000,"Annex Weight Room":80,"Extension Weight Room":55,"Main Weight Room":70,"Weight Rooms":68},{"Date":1666108451000,"Annex Weight Room":76,"Extension Weight Room":50,"Main Weight Room":70,"Weight Rooms":67},{"Date":1666108752000,"Annex Weight Room":63,"Extension Weight Room":57,"Main Weight Room":72,"Weight Rooms":66},{"Date":1666109053000,"Annex Weight Room":76,"Extension Weight Room":60,"Main Weight Room":72,"Weight Rooms":70},{"Date":1666109353000,"Annex Weight Room":66,"Extension Weight Room":60,"Main Weight Room":80,"Weight Rooms":72},{"Date":1666109654000,"Annex Weight Room":73,"Extension Weight Room":67,"Main Weight Room":66,"Weight Rooms":68},{"Date":1666109955000,"Annex Weight Room":90,"Extension Weight Room":52,"Main Weight Room":66,"Weight Rooms":66},{"Date":1666110255000,"Annex Weight Room":70,"Extension Weight Room":55,"Main Weight Room":71,"Weight Rooms":65},{"Date":1666110556000,"Annex Weight Room":60,"Extension Weight Room":57,"Main Weight Room":73,"Weight Rooms":66},{"Date":1666110856000,"Annex Weight Room":70,"Extension Weight Room":57,"Main Weight Room":71,"Weight Rooms":67},{"Date":1666111157000,"Annex Weight Room":70,"Extension Weight Room":55,"Main Weight Room":85,"Weight Rooms":73},{"Date":1666111458000,"Annex Weight Room":83,"Extension Weight Room":52,"Main Weight Room":76,"Weight Rooms":71},{"Date":1666111758000,"Annex Weight Room":83,"Extension Weight Room":67,"Main Weight Room":76,"Weight Rooms":75},{"Date":1666112059000,"Annex Weight Room":93,"Extension Weight Room":70,"Main Weight Room":80,"Weight Rooms":79},{"Date":1666112360000,"Annex Weight Room":96,"Extension Weight Room":80,"Main Weight Room":82,"Weight Rooms":84},{"Date":1666112660000,"Annex Weight Room":103,"Extension Weight Room":70,"Main Weight Room":81,"Weight Rooms":82},{"Date":1666112961000,"Annex Weight Room":100,"Extension Weight Room":65,"Main Weight Room":87,"Weight Rooms":83},{"Date":1666113261000,"Annex Weight Room":90,"Extension Weight Room":62,"Main Weight Room":92,"Weight Rooms":84},{"Date":1666113562000,"Annex Weight Room":80,"Extension Weight Room":70,"Main Weight Room":90,"Weight Rooms":83},{"Date":1666113863000,"Annex Weight Room":86,"Extension Weight Room":72,"Main Weight Room":85,"Weight Rooms":81},{"Date":1666114163000,"Annex Weight Room":106,"Extension Weight Room":65,"Main Weight Room":80,"Weight Rooms":81},{"Date":1666114464000,"Annex Weight Room":110,"Extension Weight Room":72,"Main Weight Room":67,"Weight Rooms":77},{"Date":1666114765000,"Annex Weight Room":86,"Extension Weight Room":87,"Main Weight Room":68,"Weight Rooms":77},{"Date":1666115065000,"Annex Weight Room":96,"Extension Weight Room":75,"Main Weight Room":77,"Weight Rooms":80},{"Date":1666115366000,"Annex Weight Room":90,"Extension Weight Room":75,"Main Weight Room":78,"Weight Rooms":81},{"Date":1666115667000,"Annex Weight Room":83,"Extension Weight Room":82,"Main Weight Room":68,"Weight Rooms":75},{"Date":1666115967000,"Annex Weight Room":76,"Extension Weight Room":70,"Main Weight Room":72,"Weight Rooms":72},{"Date":1666116268000,"Annex Weight Room":86,"Extension Weight Room":75,"Main Weight Room":61,"Weight Rooms":70},{"Date":1666116568000,"Annex Weight Room":86,"Extension Weight Room":57,"Main Weight Room":63,"Weight Rooms":66},{"Date":1666116869000,"Annex Weight Room":73,"Extension Weight Room":67,"Main Weight Room":61,"Weight Rooms":65},{"Date":1666117170000,"Annex Weight Room":73,"Extension Weight Room":65,"Main Weight Room":65,"Weight Rooms":66},{"Date":1666117470000,"Annex Weight Room":73,"Extension Weight Room":77,"Main Weight Room":73,"Weight Rooms":74},{"Date":1666117771000,"Annex Weight Room":73,"Extension Weight Room":77,"Main Weight Room":80,"Weight Rooms":78},{"Date":1666118072000,"Annex Weight Room":93,"Extension Weight Room":85,"Main Weight Room":73,"Weight Rooms":80},{"Date":1666118372000,"Annex Weight Room":80,"Extension Weight Room":77,"Main Weight Room":82,"Weight Rooms":81},{"Date":1666118673000,"Annex Weight Room":73,"Extension Weight Room":65,"Main Weight Room":81,"Weight Rooms":75},{"Date":1666118974000,"Annex Weight Room":63,"Extension Weight Room":72,"Main Weight Room":81,"Weight Rooms":76},{"Date":1666119274000,"Annex Weight Room":70,"Extension Weight Room":80,"Main Weight Room":81,"Weight Rooms":79},{"Date":1666119575000,"Annex Weight Room":73,"Extension Weight Room":80,"Main Weight Room":82,"Weight Rooms":80},{"Date":1666119875000,"Annex Weight Room":70,"Extension Weight Room":80,"Main Weight Room":72,"Weight Rooms":75},{"Date":1666120176000,"Annex Weight Room":60,"Extension Weight Room":77,"Main Weight Room":77,"Weight Rooms":74},{"Date":1666120477000,"Annex Weight Room":73,"Extension Weight Room":67,"Main Weight Room":71,"Weight Rooms":70},{"Date":1666120777000,"Annex Weight Room":60,"Extension Weight Room":75,"Main Weight Room":73,"Weight Rooms":71},{"Date":1666121078000,"Annex Weight Room":63,"Extension Weight Room":82,"Main Weight Room":68,"Weight Rooms":72},{"Date":1666121379000,"Annex Weight Room":76,"Extension Weight Room":67,"Main Weight Room":67,"Weight Rooms":69},{"Date":1666121679000,"Annex Weight Room":66,"Extension Weight Room":77,"Main Weight Room":70,"Weight Rooms":71},{"Date":1666121980000,"Annex Weight Room":73,"Extension Weight Room":77,"Main Weight Room":70,"Weight Rooms":72},{"Date":1666122280000,"Annex Weight Room":63,"Extension Weight Room":87,"Main Weight Room":72,"Weight Rooms":74},{"Date":1666122581000,"Annex Weight Room":60,"Extension Weight Room":67,"Main Weight Room":76,"Weight Rooms":70},{"Date":1666122882000,"Annex Weight Room":63,"Extension Weight Room":70,"Main Weight Room":77,"Weight Rooms":74},{"Date":1666123183000,"Annex Weight Room":63,"Extension Weight Room":80,"Main Weight Room":72,"Weight Rooms":73},{"Date":1666123483000,"Annex Weight Room":66,"Extension Weight Room":82,"Main Weight Room":65,"Weight Rooms":70},{"Date":1666123784000,"Annex Weight Room":53,"Extension Weight Room":77,"Main Weight Room":76,"Weight Rooms":72},{"Date":1666124084000,"Annex Weight Room":56,"Extension Weight Room":77,"Main Weight Room":72,"Weight Rooms":72},{"Date":1666124385000,"Annex Weight Room":76,"Extension Weight Room":67,"Main Weight Room":75,"Weight Rooms":72},{"Date":1666124686000,"Annex Weight Room":70,"Extension Weight Room":70,"Main Weight Room":77,"Weight Rooms":74},{"Date":1666124986000,"Annex Weight Room":66,"Extension Weight Room":65,"Main Weight Room":73,"Weight Rooms":70},{"Date":1666125287000,"Annex Weight Room":63,"Extension Weight Room":65,"Main Weight Room":70,"Weight Rooms":67},{"Date":1666125587000,"Annex Weight Room":50,"Extension Weight Room":72,"Main Weight Room":63,"Weight Rooms":64},{"Date":1666125888000,"Annex Weight Room":50,"Extension Weight Room":70,"Main Weight Room":62,"Weight Rooms":62},{"Date":1666126189000,"Annex Weight Room":33,"Extension Weight Room":62,"Main Weight Room":70,"Weight Rooms":59},{"Date":1666126489000,"Annex Weight Room":40,"Extension Weight Room":65,"Main Weight Room":61,"Weight Rooms":57},{"Date":1666126790000,"Annex Weight Room":40,"Extension Weight Room":62,"Main Weight Room":62,"Weight Rooms":57},{"Date":1666127090000,"Annex Weight Room":50,"Extension Weight Room":50,"Main Weight Room":66,"Weight Rooms":58},{"Date":1666127391000,"Annex Weight Room":43,"Extension Weight Room":50,"Main Weight Room":60,"Weight Rooms":54},{"Date":1666127692000,"Annex Weight Room":40,"Extension Weight Room":55,"Main Weight Room":63,"Weight Rooms":56},{"Date":1666127992000,"Annex Weight Room":76,"Extension Weight Room":55,"Main Weight Room":72,"Weight Rooms":68},{"Date":1666128293000,"Annex Weight Room":76,"Extension Weight Room":52,"Main Weight Room":86,"Weight Rooms":72},{"Date":1666128594000,"Annex Weight Room":90,"Extension Weight Room":72,"Main Weight Room":78,"Weight Rooms":79},{"Date":1666128894000,"Annex Weight Room":80,"Extension Weight Room":65,"Main Weight Room":86,"Weight Rooms":80},{"Date":1666129195000,"Annex Weight Room":80,"Extension Weight Room":57,"Main Weight Room":87,"Weight Rooms":78},{"Date":1666129495000,"Annex Weight Room":83,"Extension Weight Room":70,"Main Weight Room":86,"Weight Rooms":81},{"Date":1666129796000,"Annex Weight Room":96,"Extension Weight Room":75,"Main Weight Room":81,"Weight Rooms":82},{"Date":1666130097000,"Annex Weight Room":100,"Extension Weight Room":57,"Main Weight Room":82,"Weight Rooms":79},{"Date":1666130397000,"Annex Weight Room":80,"Extension Weight Room":75,"Main Weight Room":92,"Weight Rooms":84},{"Date":1666130698000,"Annex Weight Room":70,"Extension Weight Room":67,"Main Weight Room":98,"Weight Rooms":85},{"Date":1666130998000,"Annex Weight Room":93,"Extension Weight Room":82,"Main Weight Room":95,"Weight Rooms":92},{"Date":1666131299000,"Annex Weight Room":110,"Extension Weight Room":92,"Main Weight Room":92,"Weight Rooms":95},{"Date":1666131600000,"Annex Weight Room":96,"Extension Weight Room":90,"Main Weight Room":102,"Weight Rooms":97},{"Date":1666131900000,"Annex Weight Room":96,"Extension Weight Room":90,"Main Weight Room":100,"Weight Rooms":96},{"Date":1666132201000,"Annex Weight Room":83,"Extension Weight Room":82,"Main Weight Room":98,"Weight Rooms":92},{"Date":1666132501000,"Annex Weight Room":76,"Extension Weight Room":92,"Main Weight Room":93,"Weight Rooms":89},{"Date":1666132802000,"Annex Weight Room":86,"Extension Weight Room":65,"Main Weight Room":83,"Weight Rooms":79},{"Date":1666133103000,"Annex Weight Room":63,"Extension Weight Room":62,"Main Weight Room":86,"Weight Rooms":75},{"Date":1666133403000,"Annex Weight Room":100,"Extension Weight Room":70,"Main Weight Room":83,"Weight Rooms":83},{"Date":1666133704000,"Annex Weight Room":116,"Extension Weight Room":92,"Main Weight Room":98,"Weight Rooms":98},{"Date":1666134005000,"Annex Weight Room":100,"Extension Weight Room":77,"Main Weight Room":100,"Weight Rooms":94},{"Date":1666134305000,"Annex Weight Room":96,"Extension Weight Room":85,"Main Weight Room":108,"Weight Rooms":98},{"Date":1666134606000,"Annex Weight Room":113,"Extension Weight Room":100,"Main Weight Room":100,"Weight Rooms":101},{"Date":1666134906000,"Annex Weight Room":90,"Extension Weight Room":95,"Main Weight Room":106,"Weight Rooms":100},{"Date":1666135207000,"Annex Weight Room":96,"Extension Weight Room":77,"Main Weight Room":114,"Weight Rooms":101},{"Date":1666135508000,"Annex Weight Room":86,"Extension Weight Room":85,"Main Weight Room":111,"Weight Rooms":100},{"Date":1666135808000,"Annex Weight Room":86,"Extension Weight Room":92,"Main Weight Room":107,"Weight Rooms":99},{"Date":1666136109000,"Annex Weight Room":110,"Extension Weight Room":75,"Main Weight Room":110,"Weight Rooms":100},{"Date":1666136410000,"Annex Weight Room":113,"Extension Weight Room":85,"Main Weight Room":102,"Weight Rooms":100},{"Date":1666136710000,"Annex Weight Room":106,"Extension Weight Room":110,"Main Weight Room":96,"Weight Rooms":102},{"Date":1666137011000,"Annex Weight Room":90,"Extension Weight Room":105,"Main Weight Room":100,"Weight Rooms":99},{"Date":1666137312000,"Annex Weight Room":86,"Extension Weight Room":95,"Main Weight Room":92,"Weight Rooms":92},{"Date":1666656181000,"Annex Weight Room":96,"Extension Weight Room":102,"Main Weight Room":98,"Weight Rooms":99},{"Date":1666656482000,"Annex Weight Room":86,"Extension Weight Room":100,"Main Weight Room":97,"Weight Rooms":94},{"Date":1666656782000,"Annex Weight Room":103,"Extension Weight Room":97,"Main Weight Room":92,"Weight Rooms":95},{"Date":1666657083000,"Annex Weight Room":90,"Extension Weight Room":105,"Main Weight Room":101,"Weight Rooms":98},{"Date":1666657383000,"Annex Weight Room":93,"Extension Weight Room":97,"Main Weight Room":103,"Weight Rooms":98},{"Date":1666657684000,"Annex Weight Room":93,"Extension Weight Room":102,"Main Weight Room":101,"Weight Rooms":98},{"Date":1666657985000,"Annex Weight Room":123,"Extension Weight Room":75,"Main Weight Room":100,"Weight Rooms":97},{"Date":1666658285000,"Annex Weight Room":110,"Extension Weight Room":87,"Main Weight Room":98,"Weight Rooms":96},{"Date":1666658586000,"Annex Weight Room":113,"Extension Weight Room":80,"Main Weight Room":100,"Weight Rooms":96},{"Date":1666658886000,"Annex Weight Room":123,"Extension Weight Room":72,"Main Weight Room":106,"Weight Rooms":99},{"Date":1666659187000,"Annex Weight Room":110,"Extension Weight Room":72,"Main Weight Room":114,"Weight Rooms":100},{"Date":1666659488000,"Annex Weight Room":116,"Extension Weight Room":72,"Main Weight Room":110,"Weight Rooms":99},{"Date":1666659788000,"Annex Weight Room":146,"Extension Weight Room":65,"Main Weight Room":105,"Weight Rooms":100},{"Date":1666660089000,"Annex Weight Room":116,"Extension Weight Room":65,"Main Weight Room":113,"Weight Rooms":100},{"Date":1666660390000,"Annex Weight Room":103,"Extension Weight Room":95,"Main Weight Room":103,"Weight Rooms":100},{"Date":1666660690000,"Annex Weight Room":123,"Extension Weight Room":82,"Main Weight Room":102,"Weight Rooms":100},{"Date":1666660991000,"Annex Weight Room":116,"Extension Weight Room":100,"Main Weight Room":101,"Weight Rooms":102},{"Date":1666661291000,"Annex Weight Room":113,"Extension Weight Room":90,"Main Weight Room":93,"Weight Rooms":94},{"Date":1666661592000,"Annex Weight Room":106,"Extension Weight Room":85,"Main Weight Room":101,"Weight Rooms":96},{"Date":1666661893000,"Annex Weight Room":113,"Extension Weight Room":72,"Main Weight Room":97,"Weight Rooms":93},{"Date":1666662193000,"Annex Weight Room":116,"Extension Weight Room":82,"Main Weight Room":101,"Weight Rooms":98},{"Date":1666662494000,"Annex Weight Room":113,"Extension Weight Room":80,"Main Weight Room":105,"Weight Rooms":98},{"Date":1666662794000,"Annex Weight Room":120,"Extension Weight Room":87,"Main Weight Room":101,"Weight Rooms":100},{"Date":1666663095000,"Annex Weight Room":96,"Extension Weight Room":95,"Main Weight Room":98,"Weight Rooms":96},{"Date":1666663396000,"Annex Weight Room":96,"Extension Weight Room":85,"Main Weight Room":107,"Weight Rooms":98},{"Date":1666663696000,"Annex Weight Room":96,"Extension Weight Room":92,"Main Weight Room":111,"Weight Rooms":102},{"Date":1666663997000,"Annex Weight Room":103,"Extension Weight Room":92,"Main Weight Room":112,"Weight Rooms":104},{"Date":1666664298000,"Annex Weight Room":93,"Extension Weight Room":90,"Main Weight Room":118,"Weight Rooms":104},{"Date":1666664598000,"Annex Weight Room":110,"Extension Weight Room":112,"Main Weight Room":111,"Weight Rooms":109},{"Date":1666664899000,"Annex Weight Room":106,"Extension Weight Room":114,"Main Weight Room":105,"Weight Rooms":106},{"Date":1666665199000,"Annex Weight Room":116,"Extension Weight Room":87,"Main Weight Room":113,"Weight Rooms":106},{"Date":1666665500000,"Annex Weight Room":116,"Extension Weight Room":90,"Main Weight Room":110,"Weight Rooms":104},{"Date":1666665801000,"Annex Weight Room":116,"Extension Weight Room":87,"Main Weight Room":111,"Weight Rooms":104},{"Date":1666666101000,"Annex Weight Room":113,"Extension Weight Room":80,"Main Weight Room":116,"Weight Rooms":104},{"Date":1666666402000,"Annex Weight Room":110,"Extension Weight Room":102,"Main Weight Room":108,"Weight Rooms":106},{"Date":1666666702000,"Annex Weight Room":120,"Extension Weight Room":97,"Main Weight Room":105,"Weight Rooms":104},{"Date":1666667003000,"Annex Weight Room":130,"Extension Weight Room":114,"Main Weight Room":88,"Weight Rooms":102},{"Date":1666667304000,"Annex Weight Room":83,"Extension Weight Room":130,"Main Weight Room":100,"Weight Rooms":103},{"Date":1666667604000,"Annex Weight Room":103,"Extension Weight Room":110,"Main Weight Room":102,"Weight Rooms":103},{"Date":1666667905000,"Annex Weight Room":113,"Extension Weight Room":112,"Main Weight Room":97,"Weight Rooms":103},{"Date":1666668205000,"Annex Weight Room":133,"Extension Weight Room":80,"Main Weight Room":107,"Weight Rooms":104},{"Date":1666668506000,"Annex Weight Room":123,"Extension Weight Room":92,"Main Weight Room":105,"Weight Rooms":104},{"Date":1666668807000,"Annex Weight Room":136,"Extension Weight Room":92,"Main Weight Room":97,"Weight Rooms":102},{"Date":1666669107000,"Annex Weight Room":120,"Extension Weight Room":90,"Main Weight Room":102,"Weight Rooms":101},{"Date":1666669408000,"Annex Weight Room":110,"Extension Weight Room":105,"Main Weight Room":98,"Weight Rooms":100},{"Date":1666669708000,"Annex Weight Room":93,"Extension Weight Room":102,"Main Weight Room":105,"Weight Rooms":100},{"Date":1666670009000,"Annex Weight Room":110,"Extension Weight Room":95,"Main Weight Room":100,"Weight Rooms":100},{"Date":1666670310000,"Annex Weight Room":103,"Extension Weight Room":102,"Main Weight Room":103,"Weight Rooms":102},{"Date":1666670610000,"Annex Weight Room":90,"Extension Weight Room":102,"Main Weight Room":111,"Weight Rooms":103},{"Date":1666670911000,"Annex Weight Room":86,"Extension Weight Room":107,"Main Weight Room":108,"Weight Rooms":102},{"Date":1666671212000,"Annex Weight Room":96,"Extension Weight Room":114,"Main Weight Room":102,"Weight Rooms":103},{"Date":1666671512000,"Annex Weight Room":90,"Extension Weight Room":122,"Main Weight Room":102,"Weight Rooms":104},{"Date":1666671813000,"Annex Weight Room":76,"Extension Weight Room":130,"Main Weight Room":106,"Weight Rooms":105},{"Date":1666672114000,"Annex Weight Room":80,"Extension Weight Room":100,"Main Weight Room":112,"Weight Rooms":101},{"Date":1666672414000,"Annex Weight Room":73,"Extension Weight Room":105,"Main Weight Room":106,"Weight Rooms":98},{"Date":1666672715000,"Annex Weight Room":80,"Extension Weight Room":100,"Main Weight Room":105,"Weight Rooms":97},{"Date":1666673015000,"Annex Weight Room":83,"Extension Weight Room":95,"Main Weight Room":106,"Weight Rooms":97},{"Date":1666673316000,"Annex Weight Room":90,"Extension Weight Room":77,"Main Weight Room":103,"Weight Rooms":92},{"Date":1666673617000,"Annex Weight Room":113,"Extension Weight Room":80,"Main Weight Room":103,"Weight Rooms":98},{"Date":1666673917000,"Annex Weight Room":83,"Extension Weight Room":97,"Main Weight Room":106,"Weight Rooms":97},{"Date":1666674218000,"Annex Weight Room":83,"Extension Weight Room":120,"Main Weight Room":107,"Weight Rooms":104},{"Date":1666674518000,"Annex Weight Room":73,"Extension Weight Room":107,"Main Weight Room":102,"Weight Rooms":96},{"Date":1666674820000,"Annex Weight Room":56,"Extension Weight Room":95,"Main Weight Room":106,"Weight Rooms":92},{"Date":1666675120000,"Annex Weight Room":113,"Extension Weight Room":85,"Main Weight Room":90,"Weight Rooms":92},{"Date":1666675421000,"Annex Weight Room":86,"Extension Weight Room":95,"Main Weight Room":90,"Weight Rooms":89},{"Date":1666675721000,"Annex Weight Room":83,"Extension Weight Room":112,"Main Weight Room":82,"Weight Rooms":89},{"Date":1666676022000,"Annex Weight Room":63,"Extension Weight Room":114,"Main Weight Room":81,"Weight Rooms":85},{"Date":1666676323000,"Annex Weight Room":53,"Extension Weight Room":122,"Main Weight Room":67,"Weight Rooms":78},{"Date":1666676623000,"Annex Weight Room":56,"Extension Weight Room":82,"Main Weight Room":68,"Weight Rooms":68},{"Date":1666676924000,"Annex Weight Room":36,"Extension Weight Room":72,"Main Weight Room":62,"Weight Rooms":58},{"Date":1666677225000,"Annex Weight Room":13,"Extension Weight Room":75,"Main Weight Room":46,"Weight Rooms":46},{"Date":1666677525000,"Annex Weight Room":3,"Extension Weight Room":22,"Main Weight Room":31,"Weight Rooms":21},{"Date":1666706684000,"Annex Weight Room":26,"Extension Weight Room":7,"Main Weight Room":22,"Weight Rooms":19},{"Date":1666706985000,"Annex Weight Room":43,"Extension Weight Room":12,"Main Weight Room":36,"Weight Rooms":31},{"Date":1666707286000,"Annex Weight Room":46,"Extension Weight Room":15,"Main Weight Room":51,"Weight Rooms":40},{"Date":1666707586000,"Annex Weight Room":53,"Extension Weight Room":20,"Main Weight Room":60,"Weight Rooms":48},{"Date":1666707887000,"Annex Weight Room":66,"Extension Weight Room":35,"Main Weight Room":63,"Weight Rooms":56},{"Date":1666708188000,"Annex Weight Room":70,"Extension Weight Room":40,"Main Weight Room":61,"Weight Rooms":57},{"Date":1666708488000,"Annex Weight Room":70,"Extension Weight Room":50,"Main Weight Room":65,"Weight Rooms":62},{"Date":1666708789000,"Annex Weight Room":63,"Extension Weight Room":62,"Main Weight Room":70,"Weight Rooms":66},{"Date":1666709089000,"Annex Weight Room":66,"Extension Weight Room":67,"Main Weight Room":75,"Weight Rooms":71},{"Date":1666709390000,"Annex Weight Room":66,"Extension Weight Room":70,"Main Weight Room":83,"Weight Rooms":76},{"Date":1666709691000,"Annex Weight Room":76,"Extension Weight Room":57,"Main Weight Room":75,"Weight Rooms":70},{"Date":1666709991000,"Annex Weight Room":70,"Extension Weight Room":62,"Main Weight Room":73,"Weight Rooms":70},{"Date":1666710292000,"Annex Weight Room":73,"Extension Weight Room":65,"Main Weight Room":66,"Weight Rooms":67},{"Date":1666710592000,"Annex Weight Room":83,"Extension Weight Room":67,"Main Weight Room":56,"Weight Rooms":64},{"Date":1666710893000,"Annex Weight Room":96,"Extension Weight Room":62,"Main Weight Room":60,"Weight Rooms":68},{"Date":1666711194000,"Annex Weight Room":93,"Extension Weight Room":57,"Main Weight Room":61,"Weight Rooms":66},{"Date":1666711494000,"Annex Weight Room":66,"Extension Weight Room":72,"Main Weight Room":63,"Weight Rooms":66},{"Date":1666711795000,"Annex Weight Room":56,"Extension Weight Room":70,"Main Weight Room":56,"Weight Rooms":60},{"Date":1666712095000,"Annex Weight Room":60,"Extension Weight Room":67,"Main Weight Room":52,"Weight Rooms":57},{"Date":1666712396000,"Annex Weight Room":60,"Extension Weight Room":67,"Main Weight Room":55,"Weight Rooms":59},{"Date":1666712697000,"Annex Weight Room":53,"Extension Weight Room":62,"Main Weight Room":55,"Weight Rooms":56},{"Date":1666712997000,"Annex Weight Room":70,"Extension Weight Room":65,"Main Weight Room":57,"Weight Rooms":62},{"Date":1666713298000,"Annex Weight Room":56,"Extension Weight Room":62,"Main Weight Room":67,"Weight Rooms":64},{"Date":1666713599000,"Annex Weight Room":63,"Extension Weight Room":67,"Main Weight Room":65,"Weight Rooms":65},{"Date":1666713899000,"Annex Weight Room":53,"Extension Weight Room":67,"Main Weight Room":60,"Weight Rooms":60},{"Date":1666714200000,"Annex Weight Room":63,"Extension Weight Room":57,"Main Weight Room":53,"Weight Rooms":57},{"Date":1666714500000,"Annex Weight Room":63,"Extension Weight Room":60,"Main Weight Room":50,"Weight Rooms":56},{"Date":1666714801000,"Annex Weight Room":63,"Extension Weight Room":40,"Main Weight Room":56,"Weight Rooms":53},{"Date":1666715102000,"Annex Weight Room":56,"Extension Weight Room":55,"Main Weight Room":65,"Weight Rooms":60},{"Date":1666715402000,"Annex Weight Room":56,"Extension Weight Room":65,"Main Weight Room":60,"Weight Rooms":60},{"Date":1666715703000,"Annex Weight Room":53,"Extension Weight Room":55,"Main Weight Room":67,"Weight Rooms":61},{"Date":1666716003000,"Annex Weight Room":70,"Extension Weight Room":67,"Main Weight Room":66,"Weight Rooms":66},{"Date":1666716304000,"Annex Weight Room":80,"Extension Weight Room":60,"Main Weight Room":73,"Weight Rooms":71},{"Date":1666716605000,"Annex Weight Room":93,"Extension Weight Room":72,"Main Weight Room":71,"Weight Rooms":75},{"Date":1666716905000,"Annex Weight Room":93,"Extension Weight Room":62,"Main Weight Room":73,"Weight Rooms":75},{"Date":1666717206000,"Annex Weight Room":73,"Extension Weight Room":62,"Main Weight Room":72,"Weight Rooms":70},{"Date":1666717506000,"Annex Weight Room":96,"Extension Weight Room":42,"Main Weight Room":75,"Weight Rooms":72},{"Date":1666717807000,"Annex Weight Room":100,"Extension Weight Room":55,"Main Weight Room":78,"Weight Rooms":77},{"Date":1666718108000,"Annex Weight Room":103,"Extension Weight Room":60,"Main Weight Room":82,"Weight Rooms":78},{"Date":1666718409000,"Annex Weight Room":86,"Extension Weight Room":65,"Main Weight Room":80,"Weight Rooms":78},{"Date":1666718709000,"Annex Weight Room":83,"Extension Weight Room":70,"Main Weight Room":85,"Weight Rooms":80},{"Date":1666719010000,"Annex Weight Room":86,"Extension Weight Room":65,"Main Weight Room":81,"Weight Rooms":80},{"Date":1666719310000,"Annex Weight Room":96,"Extension Weight Room":70,"Main Weight Room":87,"Weight Rooms":85},{"Date":1666719611000,"Annex Weight Room":116,"Extension Weight Room":65,"Main Weight Room":86,"Weight Rooms":86},{"Date":1666719912000,"Annex Weight Room":83,"Extension Weight Room":72,"Main Weight Room":77,"Weight Rooms":77},{"Date":1666720212000,"Annex Weight Room":93,"Extension Weight Room":85,"Main Weight Room":62,"Weight Rooms":75},{"Date":1666720513000,"Annex Weight Room":83,"Extension Weight Room":72,"Main Weight Room":66,"Weight Rooms":72},{"Date":1666720814000,"Annex Weight Room":93,"Extension Weight Room":70,"Main Weight Room":66,"Weight Rooms":73},{"Date":1666721114000,"Annex Weight Room":83,"Extension Weight Room":62,"Main Weight Room":62,"Weight Rooms":67},{"Date":1666721415000,"Annex Weight Room":86,"Extension Weight Room":47,"Main Weight Room":57,"Weight Rooms":60},{"Date":1666721715000,"Annex Weight Room":93,"Extension Weight Room":52,"Main Weight Room":63,"Weight Rooms":66},{"Date":1666722016000,"Annex Weight Room":93,"Extension Weight Room":55,"Main Weight Room":68,"Weight Rooms":69},{"Date":1666722317000,"Annex Weight Room":100,"Extension Weight Room":55,"Main Weight Room":78,"Weight Rooms":78},{"Date":1666722617000,"Annex Weight Room":106,"Extension Weight Room":75,"Main Weight Room":83,"Weight Rooms":86},{"Date":1666722918000,"Annex Weight Room":116,"Extension Weight Room":80,"Main Weight Room":82,"Weight Rooms":88},{"Date":1666723218000,"Annex Weight Room":116,"Extension Weight Room":70,"Main Weight Room":77,"Weight Rooms":84},{"Date":1666723519000,"Annex Weight Room":100,"Extension Weight Room":82,"Main Weight Room":87,"Weight Rooms":88},{"Date":1666723820000,"Annex Weight Room":106,"Extension Weight Room":87,"Main Weight Room":78,"Weight Rooms":86},{"Date":1666724120000,"Annex Weight Room":100,"Extension Weight Room":92,"Main Weight Room":72,"Weight Rooms":82},{"Date":1666724421000,"Annex Weight Room":83,"Extension Weight Room":95,"Main Weight Room":78,"Weight Rooms":84},{"Date":1666724722000,"Annex Weight Room":106,"Extension Weight Room":85,"Main Weight Room":78,"Weight Rooms":86},{"Date":1666725022000,"Annex Weight Room":120,"Extension Weight Room":72,"Main Weight Room":83,"Weight Rooms":88},{"Date":1666725323000,"Annex Weight Room":93,"Extension Weight Room":62,"Main Weight Room":86,"Weight Rooms":81},{"Date":1666725624000,"Annex Weight Room":90,"Extension Weight Room":65,"Main Weight Room":77,"Weight Rooms":76},{"Date":1666725924000,"Annex Weight Room":100,"Extension Weight Room":57,"Main Weight Room":80,"Weight Rooms":78},{"Date":1666726225000,"Annex Weight Room":106,"Extension Weight Room":55,"Main Weight Room":82,"Weight Rooms":78},{"Date":1666726526000,"Annex Weight Room":103,"Extension Weight Room":60,"Main Weight Room":77,"Weight Rooms":76},{"Date":1666726826000,"Annex Weight Room":100,"Extension Weight Room":57,"Main Weight Room":83,"Weight Rooms":80},{"Date":1666727127000,"Annex Weight Room":110,"Extension Weight Room":77,"Main Weight Room":81,"Weight Rooms":87},{"Date":1666727427000,"Annex Weight Room":123,"Extension Weight Room":82,"Main Weight Room":73,"Weight Rooms":87},{"Date":1666727728000,"Annex Weight Room":126,"Extension Weight Room":75,"Main Weight Room":81,"Weight Rooms":88},{"Date":1666728029000,"Annex Weight Room":123,"Extension Weight Room":77,"Main Weight Room":86,"Weight Rooms":91},{"Date":1666728329000,"Annex Weight Room":130,"Extension Weight Room":67,"Main Weight Room":90,"Weight Rooms":88},{"Date":1666728630000,"Annex Weight Room":123,"Extension Weight Room":80,"Main Weight Room":93,"Weight Rooms":96},{"Date":1666728930000,"Annex Weight Room":126,"Extension Weight Room":85,"Main Weight Room":87,"Weight Rooms":94},{"Date":1666729231000,"Annex Weight Room":110,"Extension Weight Room":85,"Main Weight Room":78,"Weight Rooms":86},{"Date":1666729532000,"Annex Weight Room":106,"Extension Weight Room":90,"Main Weight Room":75,"Weight Rooms":85},{"Date":1666729832000,"Annex Weight Room":113,"Extension Weight Room":72,"Main Weight Room":83,"Weight Rooms":86},{"Date":1666730133000,"Annex Weight Room":103,"Extension Weight Room":87,"Main Weight Room":77,"Weight Rooms":86},{"Date":1666730433000,"Annex Weight Room":90,"Extension Weight Room":72,"Main Weight Room":83,"Weight Rooms":82},{"Date":1666730734000,"Annex Weight Room":100,"Extension Weight Room":80,"Main Weight Room":76,"Weight Rooms":82},{"Date":1666731035000,"Annex Weight Room":116,"Extension Weight Room":55,"Main Weight Room":73,"Weight Rooms":78},{"Date":1666731336000,"Annex Weight Room":106,"Extension Weight Room":60,"Main Weight Room":68,"Weight Rooms":74},{"Date":1666731636000,"Annex Weight Room":93,"Extension Weight Room":42,"Main Weight Room":82,"Weight Rooms":74},{"Date":1666731937000,"Annex Weight Room":110,"Extension Weight Room":47,"Main Weight Room":70,"Weight Rooms":72},{"Date":1666732237000,"Annex Weight Room":90,"Extension Weight Room":52,"Main Weight Room":70,"Weight Rooms":70},{"Date":1666732538000,"Annex Weight Room":110,"Extension Weight Room":47,"Main Weight Room":70,"Weight Rooms":72},{"Date":1666732839000,"Annex Weight Room":106,"Extension Weight Room":52,"Main Weight Room":78,"Weight Rooms":76},{"Date":1666733139000,"Annex Weight Room":110,"Extension Weight Room":47,"Main Weight Room":83,"Weight Rooms":80},{"Date":1666733440000,"Annex Weight Room":110,"Extension Weight Room":35,"Main Weight Room":100,"Weight Rooms":85},{"Date":1666733740000,"Annex Weight Room":96,"Extension Weight Room":55,"Main Weight Room":98,"Weight Rooms":86},{"Date":1666734041000,"Annex Weight Room":103,"Extension Weight Room":57,"Main Weight Room":93,"Weight Rooms":86},{"Date":1666734342000,"Annex Weight Room":126,"Extension Weight Room":47,"Main Weight Room":90,"Weight Rooms":86},{"Date":1666734642000,"Annex Weight Room":123,"Extension Weight Room":47,"Main Weight Room":88,"Weight Rooms":84},{"Date":1666734943000,"Annex Weight Room":126,"Extension Weight Room":52,"Main Weight Room":85,"Weight Rooms":84},{"Date":1666735244000,"Annex Weight Room":110,"Extension Weight Room":52,"Main Weight Room":87,"Weight Rooms":83},{"Date":1666735544000,"Annex Weight Room":90,"Extension Weight Room":62,"Main Weight Room":95,"Weight Rooms":85},{"Date":1666735845000,"Annex Weight Room":93,"Extension Weight Room":60,"Main Weight Room":87,"Weight Rooms":81},{"Date":1666736145000,"Annex Weight Room":103,"Extension Weight Room":60,"Main Weight Room":85,"Weight Rooms":83},{"Date":1666736446000,"Annex Weight Room":110,"Extension Weight Room":45,"Main Weight Room":88,"Weight Rooms":81},{"Date":1666736747000,"Annex Weight Room":126,"Extension Weight Room":35,"Main Weight Room":83,"Weight Rooms":79},{"Date":1666737047000,"Annex Weight Room":130,"Extension Weight Room":30,"Main Weight Room":80,"Weight Rooms":76},{"Date":1666737348000,"Annex Weight Room":130,"Extension Weight Room":25,"Main Weight Room":73,"Weight Rooms":72},{"Date":1666737649000,"Annex Weight Room":143,"Extension Weight Room":25,"Main Weight Room":71,"Weight Rooms":73},{"Date":1666737949000,"Annex Weight Room":143,"Extension Weight Room":37,"Main Weight Room":83,"Weight Rooms":82},{"Date":1666738250000,"Annex Weight Room":146,"Extension Weight Room":27,"Main Weight Room":77,"Weight Rooms":78},{"Date":1666738550000,"Annex Weight Room":186,"Extension Weight Room":2,"Main Weight Room":83,"Weight Rooms":82},{"Date":1666738851000,"Annex Weight Room":203,"Extension Weight Room":22,"Main Weight Room":96,"Weight Rooms":96},{"Date":1666739152000,"Annex Weight Room":203,"Extension Weight Room":40,"Main Weight Room":91,"Weight Rooms":99},{"Date":1666739452000,"Annex Weight Room":216,"Extension Weight Room":30,"Main Weight Room":93,"Weight Rooms":100},{"Date":1666739753000,"Annex Weight Room":226,"Extension Weight Room":17,"Main Weight Room":96,"Weight Rooms":100},{"Date":1666740053000,"Annex Weight Room":233,"Extension Weight Room":17,"Main Weight Room":93,"Weight Rooms":100},{"Date":1666740354000,"Annex Weight Room":233,"Extension Weight Room":5,"Main Weight Room":102,"Weight Rooms":100},{"Date":1666740655000,"Annex Weight Room":270,"Extension Weight Room":12,"Main Weight Room":93,"Weight Rooms":99},{"Date":1666740955000,"Annex Weight Room":283,"Extension Weight Room":2,"Main Weight Room":101,"Weight Rooms":100},{"Date":1666741256000,"Annex Weight Room":263,"Extension Weight Room":22,"Main Weight Room":100,"Weight Rooms":98},{"Date":1666741556000,"Annex Weight Room":253,"Extension Weight Room":50,"Main Weight Room":95,"Weight Rooms":101},{"Date":1666741857000,"Annex Weight Room":240,"Extension Weight Room":30,"Main Weight Room":106,"Weight Rooms":99},{"Date":1666742157000,"Annex Weight Room":250,"Extension Weight Room":30,"Main Weight Room":102,"Weight Rooms":99}]